{
  "api": {
    "BedrockAPI": {
      "dependsOn": [
        {
          "attributes": [
            "Name",
            "Arn"
          ],
          "category": "function",
          "resourceName": "webtoongeneratora0208b26"
        }
      ],
      "providerPlugin": "awscloudformation",
      "service": "API Gateway"
    }
  },
  "function": {
    "webtoongeneratora0208b26": {
      "build": true,
      "providerPlugin": "awscloudformation",
      "service": "Lambda"
    }
  },
  "hosting": {
    "S3AndCloudFront": {
      "providerPlugin": "awscloudformation",
      "service": "S3AndCloudFront"
    }
  },
  "parameters": {
    "AMPLIFY_function_webtoongeneratora0208b26_bedrockModel": {
      "usedBy": [
        {
          "category": "function",
          "resourceName": "webtoongeneratora0208b26"
        }
      ]
    },
    "AMPLIFY_function_webtoongeneratora0208b26_deploymentBucketName": {
      "usedBy": [
        {
          "category": "function",
          "resourceName": "webtoongeneratora0208b26"
        }
      ]
    },
    "AMPLIFY_function_webtoongeneratora0208b26_myAwsRegion": {
      "usedBy": [
        {
          "category": "function",
          "resourceName": "webtoongeneratora0208b26"
        }
      ]
    },
    "AMPLIFY_function_webtoongeneratora0208b26_s3Key": {
      "usedBy": [
        {
          "category": "function",
          "resourceName": "webtoongeneratora0208b26"
        }
      ]
    }
  }
}